evolutune/__init__.py
evolutune/tuner.py
evolutune-0.0.4.dist-info/licenses/LICENSE
evolutune-0.0.4.dist-info/METADATA
evolutune-0.0.4.dist-info/WHEEL
evolutune-0.0.4.dist-info/top_level.txt
evolutune-0.0.4.dist-info/RECORD
