Metadata-Version: 2.4
Name: evolutune
Version: 0.0.4
Summary: A hyperparameter tuning library for machine learning models based on evolutionary algorithms.
Author: torchd3v
Author-email: <burak96egeli@gmail.com>
Keywords: python,hyperparameter,tuning,genetic-algorithm,model,search,CV,evolutionary-algorithm,particle-swarm-optimization
Classifier: Development Status :: 1 - Planning
Classifier: Intended Audience :: Developers
Classifier: Programming Language :: Python :: 3
Classifier: Operating System :: Unix
Classifier: Operating System :: MacOS :: MacOS X
Classifier: Operating System :: Microsoft :: Windows
License-File: LICENSE
Requires-Dist: numpy
Requires-Dist: joblib
Requires-Dist: scikit-learn
Dynamic: author
Dynamic: author-email
Dynamic: classifier
Dynamic: description
Dynamic: description-content-type
Dynamic: keywords
Dynamic: license-file
Dynamic: requires-dist
Dynamic: summary
